Workbook

Sheet Read Me
A1: Burlington - South Burlington - Winooski Merger Study
A2: District Data Collection Template | DRAFT v0.3 | Updated October 28, 2026
A4: Submission
A5: District
A6: Prepared by (name, title)
A7: Date submitted
A9: Purpose | B9: The committee work plan asks district staff to pull and summarize data for their district in a common format. This workbook is that common format. District staff provide information; the committee does the analysis and makes the judgments.
A11: How to use it | B11: 1. Choose your district above. It fills in automatically on every tab. 2. Enter data only in yellow cells. Grey cells calculate automatically. 3. Do not add, delete, rename or reorder rows, columns or tabs. The Facilitator compiles all three districts' files by copying them into a combined workbook, so the layout must stay identical. 4. Use the definitions given. If your data uses a different definition, enter it anyway and explain in Notes and caveats. 5. The Source column is pre-filled with the expected source. Change it if you used a different one, and enter the date you pulled the data. 6. Enter percentages as decimals: 0.42 displays as 42.0%. 7. Leave a cell blank if data is unavailable, and say why in Notes. Do not enter 0 for unknown. 8. Follow AOE small-group suppression rules. Do not report any figure that could identify an individual student or employee. 9. Update the Data Inventory status as you go, then send the completed file to the Facilitator.
A14: Tabs | B14: Data Inventory: every item from the work plan's data table and its status for your district. 1 Enrollment, 2 Outcomes, 3 Finance, 4 Staffing, 5 Transportation: one row per measure and year. 6 Facilities: one row per building. 7 Programs & Supports: one row per program, partnership or student support. 8 Contracts, Debt & Property: Phase 4 items, one row per agreement, bond or property.
A16: Cell legend | B16: Enter / paste data | C16: Yellow fill, blue text
B17: Calculated | C17: Grey fill. Do not edit.
A19: Example entry | B19: Illustrative values only, to show the expected format. Not real district data.
A20: Measure | B20: Year | C20: Value as entered | D20: Displays as | E20: Source | F20: Data as of | G20: Notes
A21: Students with an IEP | B21: FY2026 | C21: 0.183 | D21: 0.183 | E21: Vermont Education Dashboard | F21: 11/10/2026 | G21: From Dec 1 child count
A23: Source of this structure | B23: Data categories, sources, timing and phases follow the "Data and information needs" table in the amended DRAFT Committee Work Plan. Individual measures within each category are proposals for the committee to accept, revise or drop. The open questions and assumptions log is kept separately by the Facilitator.

Sheet Data Inventory
A1: Data Inventory and Status
A2: From the work plan's "Data and information needs" table. Update status as items are submitted.
A3: ="District: "&IF('Read Me'!$C$5="","(choose your district on the Read Me tab)",'Read Me'!$C$5)&" | Yellow cells = enter data. Grey cells = calculated, do not edit." -> District: (choose your district on the Read Me tab) | Yellow cells = enter data. Grey cells = calculated, do not edit.
A5: ID | B5: Information | C5: Source | D5: Available | E5: Needed for | F5: Who gathers | G5: Template tab | H5: Status | I5: Target date | J5: Notes
A6: D01 | B6: Enrollment, demographics, assessment, attendance, course enrollment | C6: Vermont Education Dashboard | D6: Now | E6: Phase 1 | F6: District staff | G6: 1 Enrollment; 2 Outcomes | H6: Not started
A7: D02 | B7: Long-term weighted ADM (FY27) | C7: AOE | D7: Now | E7: Phases 1, 3 | F7: District staff | G7: 3 Finance | H7: Not started
A8: D03 | B8: Per-pupil spending and district financial reports | C8: AOE | D8: Now; FY27 spending per LTWADM not yet published | E8: Phases 1, 3 | F8: District staff | G8: 3 Finance | H8: Not started
A9: D04 | B9: Teacher and staff FTE (FY2020-FY2026) | C9: AOE | D9: Now | E9: Phases 1, 3 | F9: District staff | G9: 4 Staffing | H9: Not started
A10: D05 | B10: Facilities condition (2023 assessment) | C10: School Facilities Dashboard; district facilities records | D10: Now | E10: Phases 1, 3 | F10: District staff | G10: 6 Facilities | H10: Not started
A11: D06 | B11: Education and District Quality Standards reports; graduation requirements | C11: AOE | D11: Now | E11: Phase 1 | F11: Facilitator | G11: (Facilitator provides) | H11: n/a
A12: D07 | B12: Local program offerings, partnerships, student supports | C12: Districts | D12: On request | E12: Phases 1, 2 | F12: District staff | G12: 7 Programs & Supports | H12: Not started
A13: D08 | B13: Quality Evaluation Framework | C13: AOE and State Board | D13: December 2026 (expected) | E13: Phase 2 | F13: Facilitator | G13: (Facilitator provides) | H13: n/a
A14: D09 | B14: 2026-27 enrollment and financial data | C14: AOE | D14: December 2026 - January 2027 (expected) | E14: Phase 2 | F14: District staff | G14: 1 Enrollment; 3 Finance | H14: Not started
A15: D10 | B15: Financial, staffing and scenario-planning tools; equity index | C15: AOE | D15: February - March 2027 (expected) | E15: Phase 3 | F15: Facilitator | G15: (Facilitator provides) | H15: n/a
A16: D11 | B16: Transportation data | C16: AOE survey; districts | D16: In development | E16: Phase 3 | F16: District staff | G16: 5 Transportation | H16: Not started
A17: D12 | B17: Union contracts, debt schedules, property records | C17: Districts | D17: On request | E17: Phase 4 | F17: District staff | G17: 8 Contracts, Debt & Property | H17: Not started
G19: Items submitted | H19: =COUNTIF(H6:H17,"Submitted") -> 0
G20: Items assigned to district | H20: =COUNTA(H6:H17)-COUNTIF(H6:H17,"n/a") -> 9
G21: Percent submitted | H21: =IFERROR(H19/H20,0) -> 0

Sheet 1 Enrollment
A1: Enrollment and Demographics
A2: Needed for: Phase 1. One row per measure and year. Percentages as decimals (0.42 = 42%). Do not add, delete or reorder rows.
A3: ="District: "&IF('Read Me'!$C$5="","(choose your district on the Read Me tab)",'Read Me'!$C$5)&" | Yellow cells = enter data. Grey cells = calculated, do not edit." -> District: (choose your district on the Read Me tab) | Yellow cells = enter data. Grey cells = calculated, do not edit.
A5: ID | B5: Measure | C5: Definition / how to calculate | D5: Unit | E5: Year | F5: Value | G5: Source | H5: Data as of | I5: Notes and caveats | J5: Phase
A6: Trend
A7: E01 | B7: Total PreK-12 enrollment | C7: Students enrolled on the official October census date, PreK through grade 12. | D7: count | E7: FY2020 | G7: Vermont Education Dashboard | J7: 1
A8: E01 | B8: Total PreK-12 enrollment | C8: Students enrolled on the official October census date, PreK through grade 12. | D8: count | E8: FY2021 | G8: Vermont Education Dashboard | J8: 1
A9: E01 | B9: Total PreK-12 enrollment | C9: Students enrolled on the official October census date, PreK through grade 12. | D9: count | E9: FY2022 | G9: Vermont Education Dashboard | J9: 1
A10: E01 | B10: Total PreK-12 enrollment | C10: Students enrolled on the official October census date, PreK through grade 12. | D10: count | E10: FY2023 | G10: Vermont Education Dashboard | J10: 1
A11: E01 | B11: Total PreK-12 enrollment | C11: Students enrolled on the official October census date, PreK through grade 12. | D11: count | E11: FY2024 | G11: Vermont Education Dashboard | J11: 1
A12: E01 | B12: Total PreK-12 enrollment | C12: Students enrolled on the official October census date, PreK through grade 12. | D12: count | E12: FY2025 | G12: Vermont Education Dashboard | J12: 1
A13: E01 | B13: Total PreK-12 enrollment | C13: Students enrolled on the official October census date, PreK through grade 12. | D13: count | E13: FY2026 | G13: Vermont Education Dashboard | J13: 1
A14: E02 | B14: Total PreK-12 enrollment, FY2027 (2026-27) | C14: Same definition as E01. Expected from AOE Dec 2026 - Jan 2027. | D14: count | E14: FY2027 | G14: AOE | J14: 2
A15: FY2026 detail
A16: E03 | B16: Enrollment: PreK | D16: count | E16: FY2026 | G16: Vermont Education Dashboard | J16: 1
A17: E04 | B17: Enrollment: grades K-5 | D17: count | E17: FY2026 | G17: Vermont Education Dashboard | J17: 1
A18: E05 | B18: Enrollment: grades 6-8 | D18: count | E18: FY2026 | G18: Vermont Education Dashboard | J18: 1
A19: E06 | B19: Enrollment: grades 9-12 | D19: count | E19: FY2026 | G19: Vermont Education Dashboard | J19: 1
A20: E07 | B20: Students from low-income households | C20: Share of students identified as economically disadvantaged / eligible for free or reduced-price meals. | D20: % | E20: FY2026 | G20: Vermont Education Dashboard | J20: 1
A21: E08 | B21: Multilingual learners (English learners) | C21: Share of students identified as English learners. | D21: % | E21: FY2026 | G21: Vermont Education Dashboard | J21: 1
A22: E09 | B22: Number of home languages spoken | C22: Distinct primary home languages reported by families. | D22: count | E22: FY2026 | G22: District records | J22: 1
A23: E10 | B23: Students with an IEP | C23: Share of students on an Individualized Education Program. | D23: % | E23: FY2026 | G23: Vermont Education Dashboard | J23: 1
A24: E11 | B24: Students with a 504 plan | D24: % | E24: FY2026 | G24: District records | J24: 1
A25: E12 | B25: Students of color | C25: Share of students identifying as a race/ethnicity other than white, non-Hispanic. | D25: % | E25: FY2026 | G25: Vermont Education Dashboard | J25: 1
A26: E13 | B26: Students experiencing homelessness | C26: McKinney-Vento identified students during the year. | D26: count | E26: FY2026 | G26: District records | J26: 1
A27: Public high school choice (FY2026)
A28: E14 | B28: High school choice students going OUT: total | C28: Calculated: sum of the four rows below. | D28: count | E28: FY2026 | F28: =IF(COUNT(F29:F32)=0,"",SUM(F29:F32)) | G28: Calculated | J28: 1
A29: E15 | B29: Going out to Burlington | C29: Your resident students attending this district's high school through public high school choice. Leave blank if this is your district. | D29: count | E29: FY2026 | G29: District records | J29: 1
A30: E16 | B30: Going out to South Burlington | C30: Leave blank if this is your district. | D30: count | E30: FY2026 | G30: District records | J30: 1
A31: E17 | B31: Going out to Winooski | C31: Leave blank if this is your district. | D31: count | E31: FY2026 | G31: District records | J31: 1
A32: E18 | B32: Going out to other Vermont districts | C32: All other districts combined. | D32: count | E32: FY2026 | G32: District records | J32: 1
A33: E19 | B33: High school choice students coming IN: total | C33: Calculated: sum of the four rows below. | D33: count | E33: FY2026 | F33: =IF(COUNT(F34:F37)=0,"",SUM(F34:F37)) | G33: Calculated | J33: 1
A34: E20 | B34: Coming in from Burlington | C34: Students from this district attending your high school through public high school choice. Leave blank if this is your district. | D34: count | E34: FY2026 | G34: District records | J34: 1
A35: E21 | B35: Coming in from South Burlington | C35: Leave blank if this is your district. | D35: count | E35: FY2026 | G35: District records | J35: 1
A36: E22 | B36: Coming in from Winooski | C36: Leave blank if this is your district. | D36: count | E36: FY2026 | G36: District records | J36: 1
A37: E23 | B37: Coming in from other Vermont districts | C37: All other districts combined. | D37: count | E37: FY2026 | G37: District records | J37: 1

Sheet 2 Outcomes
A1: Student Outcomes and Opportunity
A2: Needed for: Phase 1. One row per measure and year. Percentages as decimals (0.42 = 42%). Do not add, delete or reorder rows.
A3: ="District: "&IF('Read Me'!$C$5="","(choose your district on the Read Me tab)",'Read Me'!$C$5)&" | Yellow cells = enter data. Grey cells = calculated, do not edit." -> District: (choose your district on the Read Me tab) | Yellow cells = enter data. Grey cells = calculated, do not edit.
A5: ID | B5: Measure | C5: Definition / how to calculate | D5: Unit | E5: Year | F5: Value | G5: Source | H5: Data as of | I5: Notes and caveats | J5: Phase
A6: Assessment (most recent year)
A7: O01 | B7: ELA proficiency, grades 3-8 | C7: Share scoring proficient or above on the state assessment. | D7: % | E7: FY2025 | G7: Vermont Education Dashboard | J7: 1
A8: O02 | B8: Math proficiency, grades 3-8 | D8: % | E8: FY2025 | G8: Vermont Education Dashboard | J8: 1
A9: O03 | B9: ELA proficiency, grade 9 | D9: % | E9: FY2025 | G9: Vermont Education Dashboard | J9: 1
A10: O04 | B10: Math proficiency, grade 9 | D10: % | E10: FY2025 | G10: Vermont Education Dashboard | J10: 1
A11: O05 | B11: Science proficiency (all tested grades) | D11: % | E11: FY2025 | G11: Vermont Education Dashboard | J11: 1
A12: Attendance and completion
A13: O06 | B13: Chronic absenteeism rate | C13: Share of students missing 10% or more of enrolled days. | D13: % | E13: FY2024 | G13: Vermont Education Dashboard | J13: 1
A14: O06 | B14: Chronic absenteeism rate | C14: Share of students missing 10% or more of enrolled days. | D14: % | E14: FY2025 | G14: Vermont Education Dashboard | J14: 1
A15: O07 | B15: Four-year graduation rate | D15: % | E15: FY2024 | G15: Vermont Education Dashboard | J15: 1
A16: O07 | B16: Four-year graduation rate | D16: % | E16: FY2025 | G16: Vermont Education Dashboard | J16: 1
A17: O08 | B17: Six-year graduation rate | D17: % | E17: FY2024 | G17: Vermont Education Dashboard | J17: 1
A18: O08 | B18: Six-year graduation rate | D18: % | E18: FY2025 | G18: Vermont Education Dashboard | J18: 1
A19: Course access and pathways
A20: O09 | B20: Distinct high school courses offered | C20: Count of unique course titles offered in the school year. | D20: count | E20: FY2026 | G20: Vermont Education Dashboard / district | J20: 1
A21: O10 | B21: Advanced Placement / advanced courses offered | D21: count | E21: FY2026 | G21: District records | J21: 1
A22: O11 | B22: World languages offered | D22: count | E22: FY2026 | G22: District records | J22: 1
A23: O12 | B23: Students in dual enrollment or Early College | D23: count | E23: FY2026 | G23: District records | J23: 1
A24: O13 | B24: Students enrolled in CTE programs | C24: Students attending a regional CTE center for any program. | D24: count | E24: FY2026 | G24: District / CTE center records | J24: 1
A25: O14 | B25: Students in flexible pathways (work-based learning, virtual, etc.) | D25: count | E25: FY2026 | G25: District records | J25: 1

Sheet 3 Finance
A1: Finance
A2: Needed for: Phases 1 and 3. One row per measure and year. Percentages as decimals (0.42 = 42%). Do not add, delete or reorder rows.
A3: ="District: "&IF('Read Me'!$C$5="","(choose your district on the Read Me tab)",'Read Me'!$C$5)&" | Yellow cells = enter data. Grey cells = calculated, do not edit." -> District: (choose your district on the Read Me tab) | Yellow cells = enter data. Grey cells = calculated, do not edit.
A5: ID | B5: Measure | C5: Definition / how to calculate | D5: Unit | E5: Year | F5: Value | G5: Source | H5: Data as of | I5: Notes and caveats | J5: Phase
A6: Pupil counts
A7: F01 | B7: Long-term weighted ADM (LTWADM) | C7: As published by AOE for the fiscal year. | D7: number | E7: FY2027 | G7: AOE | J7: 1, 3
A8: Spending (actual / budgeted)
A9: F02 | B9: Total general fund expenditures | D9: $ | E9: FY2024 | G9: District financial reports | J9: 1, 3
A10: F02 | B10: Total general fund expenditures | D10: $ | E10: FY2025 | G10: District financial reports | J10: 1, 3
A11: F02 | B11: Total general fund expenditures | D11: $ | E11: FY2026 | G11: District financial reports | J11: 1, 3
A12: F03 | B12: Education spending | C12: As defined in Vermont statute for the education tax calculation. | D12: $ | E12: FY2025 | G12: AOE / district budget | J12: 1, 3
A13: F03 | B13: Education spending | C13: As defined in Vermont statute for the education tax calculation. | D13: $ | E13: FY2026 | G13: AOE / district budget | J13: 1, 3
A14: F03 | B14: Education spending | C14: As defined in Vermont statute for the education tax calculation. | D14: $ | E14: FY2027 | G14: AOE / district budget | J14: 1, 3
A15: F04 | B15: Education spending per LTWADM | C15: FY2027 not yet published by AOE; leave blank until available. | D15: $ | E15: FY2025 | G15: AOE | J15: 1, 3
A16: F04 | B16: Education spending per LTWADM | C16: FY2027 not yet published by AOE; leave blank until available. | D16: $ | E16: FY2026 | G16: AOE | J16: 1, 3
A17: F04 | B17: Education spending per LTWADM | C17: FY2027 not yet published by AOE; leave blank until available. | D17: $ | E17: FY2027 | G17: AOE | J17: 1, 3
A18: F05 | B18: Special education expenditures | C18: Total, all funding sources. | D18: $ | E18: FY2025 | G18: District financial reports | J18: 1, 3
A19: F06 | B19: Transportation expenditures | D19: $ | E19: FY2025 | G19: District financial reports | J19: 3
A20: F07 | B20: Tuition paid to other schools | D20: $ | E20: FY2025 | G20: District financial reports | J20: 1, 3
A21: F08 | B21: Tuition received from other districts | D21: $ | E21: FY2025 | G21: District financial reports | J21: 1, 3
A22: F09 | B22: Federal grant revenue | D22: $ | E22: FY2025 | G22: District financial reports | J22: 1, 3
A23: Tax and fund position
A24: F10 | B24: Homestead education tax rate (equalized) | D24: rate | E24: FY2026 | G24: Vermont Dept. of Taxes / AOE | J24: 1, 3
A25: F10 | B25: Homestead education tax rate (equalized) | D25: rate | E25: FY2027 | G25: Vermont Dept. of Taxes / AOE | J25: 1, 3
A26: F11 | B26: Common level of appraisal (CLA) | C26: Enter as a percent. | D26: % | E26: FY2027 | G26: Vermont Dept. of Taxes | J26: 1, 3
A27: F12 | B27: Unassigned fund balance / reserves | C27: As of June 30 of the fiscal year. | D27: $ | E27: FY2025 | G27: Audited financial statements | J27: 3, 4
A28: F13 | B28: Outstanding long-term debt | C28: Principal outstanding as of June 30. | D28: $ | E28: FY2025 | G28: Audited financial statements | J28: 3, 4
A29: F14 | B29: Annual debt service | C29: Principal + interest paid in the year. | D29: $ | E29: FY2025 | G29: District financial reports | J29: 3, 4

Sheet 4 Staffing
A1: Staffing
A2: Needed for: Phases 1 and 3. One row per measure and year. Percentages as decimals (0.42 = 42%). Do not add, delete or reorder rows.
A3: ="District: "&IF('Read Me'!$C$5="","(choose your district on the Read Me tab)",'Read Me'!$C$5)&" | Yellow cells = enter data. Grey cells = calculated, do not edit." -> District: (choose your district on the Read Me tab) | Yellow cells = enter data. Grey cells = calculated, do not edit.
A5: ID | B5: Measure | C5: Definition / how to calculate | D5: Unit | E5: Year | F5: Value | G5: Source | H5: Data as of | I5: Notes and caveats | J5: Phase
A6: FTE trend
A7: S01 | B7: Teacher FTE | C7: Licensed classroom and specialist teachers. | D7: number | E7: FY2020 | G7: AOE staffing data | J7: 1, 3
A8: S01 | B8: Teacher FTE | C8: Licensed classroom and specialist teachers. | D8: number | E8: FY2021 | G8: AOE staffing data | J8: 1, 3
A9: S01 | B9: Teacher FTE | C9: Licensed classroom and specialist teachers. | D9: number | E9: FY2022 | G9: AOE staffing data | J9: 1, 3
A10: S01 | B10: Teacher FTE | C10: Licensed classroom and specialist teachers. | D10: number | E10: FY2023 | G10: AOE staffing data | J10: 1, 3
A11: S01 | B11: Teacher FTE | C11: Licensed classroom and specialist teachers. | D11: number | E11: FY2024 | G11: AOE staffing data | J11: 1, 3
A12: S01 | B12: Teacher FTE | C12: Licensed classroom and specialist teachers. | D12: number | E12: FY2025 | G12: AOE staffing data | J12: 1, 3
A13: S01 | B13: Teacher FTE | C13: Licensed classroom and specialist teachers. | D13: number | E13: FY2026 | G13: AOE staffing data | J13: 1, 3
A14: S02 | B14: Paraeducator FTE | D14: number | E14: FY2020 | G14: AOE staffing data | J14: 1, 3
A15: S02 | B15: Paraeducator FTE | D15: number | E15: FY2021 | G15: AOE staffing data | J15: 1, 3
A16: S02 | B16: Paraeducator FTE | D16: number | E16: FY2022 | G16: AOE staffing data | J16: 1, 3
A17: S02 | B17: Paraeducator FTE | D17: number | E17: FY2023 | G17: AOE staffing data | J17: 1, 3
A18: S02 | B18: Paraeducator FTE | D18: number | E18: FY2024 | G18: AOE staffing data | J18: 1, 3
A19: S02 | B19: Paraeducator FTE | D19: number | E19: FY2025 | G19: AOE staffing data | J19: 1, 3
A20: S02 | B20: Paraeducator FTE | D20: number | E20: FY2026 | G20: AOE staffing data | J20: 1, 3
A21: S03 | B21: Administrator FTE | C21: Principals, assistant principals, central office administrators. | D21: number | E21: FY2020 | G21: AOE staffing data | J21: 1, 3
A22: S03 | B22: Administrator FTE | C22: Principals, assistant principals, central office administrators. | D22: number | E22: FY2021 | G22: AOE staffing data | J22: 1, 3
A23: S03 | B23: Administrator FTE | C23: Principals, assistant principals, central office administrators. | D23: number | E23: FY2022 | G23: AOE staffing data | J23: 1, 3
A24: S03 | B24: Administrator FTE | C24: Principals, assistant principals, central office administrators. | D24: number | E24: FY2023 | G24: AOE staffing data | J24: 1, 3
A25: S03 | B25: Administrator FTE | C25: Principals, assistant principals, central office administrators. | D25: number | E25: FY2024 | G25: AOE staffing data | J25: 1, 3
A26: S03 | B26: Administrator FTE | C26: Principals, assistant principals, central office administrators. | D26: number | E26: FY2025 | G26: AOE staffing data | J26: 1, 3
A27: S03 | B27: Administrator FTE | C27: Principals, assistant principals, central office administrators. | D27: number | E27: FY2026 | G27: AOE staffing data | J27: 1, 3
A28: FY2026 detail
A29: S04 | B29: Special educators FTE | D29: number | E29: FY2026 | G29: AOE / district | J29: 1, 3
A30: S05 | B30: Multilingual learner (EL) teachers FTE | D30: number | E30: FY2026 | G30: District records | J30: 1, 3
A31: S06 | B31: Student support FTE (counselors, social workers, psychologists, nurses) | D31: number | E31: FY2026 | G31: District records | J31: 1, 3
A32: S07 | B32: Average teacher salary | C32: Base salary, full-time teachers. | D32: $ | E32: FY2026 | G32: District records | J32: 3
A33: S08 | B33: Average teacher years of experience | D33: years | E33: FY2026 | G33: District records | J33: 3
A34: S09 | B34: Teacher turnover rate | C34: Teachers leaving the district between FY2025 and FY2026 / FY2025 teachers. | D34: % | E34: FY2026 | G34: District records | J34: 3
A35: S10 | B35: Positions unfilled at start of year | D35: count | E35: FY2026 | G35: District records | J35: 3
A36: Calculated (do not edit)
A37: S11 | B37: Students per teacher FTE | C37: Calculated: FY2026 enrollment (tab 1, row E01) / FY2026 teacher FTE (row S01). | D37: ratio | E37: FY2026 | F37: =IFERROR('1 Enrollment'!F13/F13,"") | G37: Calculated | J37: 1, 3

Sheet 5 Transportation
A1: Transportation
A2: Needed for: Phase 3. One row per measure and year. Percentages as decimals (0.42 = 42%). Do not add, delete or reorder rows.
A3: ="District: "&IF('Read Me'!$C$5="","(choose your district on the Read Me tab)",'Read Me'!$C$5)&" | Yellow cells = enter data. Grey cells = calculated, do not edit." -> District: (choose your district on the Read Me tab) | Yellow cells = enter data. Grey cells = calculated, do not edit.
A5: ID | B5: Measure | C5: Definition / how to calculate | D5: Unit | E5: Year | F5: Value | G5: Source | H5: Data as of | I5: Notes and caveats | J5: Phase
A6: T01 | B6: Students transported daily | D6: count | E6: FY2026 | G6: District / AOE survey | J6: 3
A7: T02 | B7: Number of bus routes | D7: count | E7: FY2026 | G7: District / AOE survey | J7: 3
A8: T03 | B8: Daily route miles | D8: count | E8: FY2026 | G8: District / AOE survey | J8: 3
A9: T04 | B9: Longest one-way ride time (minutes) | D9: count | E9: FY2026 | G9: District / AOE survey | J9: 3
A10: T05 | B10: Service model | C10: District-owned, contracted, municipal transit, or mixed. | D10: text | E10: FY2026 | G10: District | J10: 3
A11: T06 | B11: Contract expiration date (if contracted) | D11: date | E11: FY2026 | G11: District | J11: 3, 4
A12: T07 | B12: Students transported to CTE or out-of-district programs | D12: count | E12: FY2026 | G12: District | J12: 3

Sheet 6 Facilities
A1: Facilities
A2: Needed for: Phases 1 and 3. One row per school building, including leased and administrative space. Condition from the 2023 statewide facilities assessment. District column fills in automatically.
A3: ="District: "&IF('Read Me'!$C$5="","(choose your district on the Read Me tab)",'Read Me'!$C$5)&" | Yellow cells = enter data. Grey cells = calculated, do not edit." -> District: (choose your district on the Read Me tab) | Yellow cells = enter data. Grey cells = calculated, do not edit.
A5: District | B5: School / building | C5: Grades served | D5: Year built (original) | E5: Major renovation year(s) | F5: Gross square feet | G5: Design / functional capacity (students) | H5: FY2026 enrollment | I5: Utilization (calculated) | J5: 2023 assessment condition rating | K5: Facility condition index (FCI), if reported | L5: Estimated deferred maintenance ($) | M5: Planned capital projects (next 5 years) | N5: Planned capital cost ($) | O5: Accessibility (ADA) gaps | P5: Source | Q5: Notes
A6: =IF(B6="","",'Read Me'!$C$5) | I6: =IFERROR(H6/G6,"")
A7: =IF(B7="","",'Read Me'!$C$5) | I7: =IFERROR(H7/G7,"")
A8: =IF(B8="","",'Read Me'!$C$5) | I8: =IFERROR(H8/G8,"")
A9: =IF(B9="","",'Read Me'!$C$5) | I9: =IFERROR(H9/G9,"")
A10: =IF(B10="","",'Read Me'!$C$5) | I10: =IFERROR(H10/G10,"")
A11: =IF(B11="","",'Read Me'!$C$5) | I11: =IFERROR(H11/G11,"")
A12: =IF(B12="","",'Read Me'!$C$5) | I12: =IFERROR(H12/G12,"")
A13: =IF(B13="","",'Read Me'!$C$5) | I13: =IFERROR(H13/G13,"")
A14: =IF(B14="","",'Read Me'!$C$5) | I14: =IFERROR(H14/G14,"")
A15: =IF(B15="","",'Read Me'!$C$5) | I15: =IFERROR(H15/G15,"")
A16: =IF(B16="","",'Read Me'!$C$5) | I16: =IFERROR(H16/G16,"")
A17: =IF(B17="","",'Read Me'!$C$5) | I17: =IFERROR(H17/G17,"")
... A25: =IF(B25="","",'Read Me'!$C$5) | I25: =IFERROR(H25/G25,"")

Sheet 7 Programs & Supports
A1: Local Programs, Partnerships and Student Supports
A2: Needed for: Phases 1 and 2. Supports the asset map and the question of which local strengths must be protected. One row per program. District column fills in automatically.
A3: ="District: "&IF('Read Me'!$C$5="","(choose your district on the Read Me tab)",'Read Me'!$C$5)&" | Yellow cells = enter data. Grey cells = calculated, do not edit." -> District: (choose your district on the Read Me tab) | Yellow cells = enter data. Grey cells = calculated, do not edit.
A5: District | B5: Program, partnership or support | C5: Category | D5: Grades served | E5: Students served (FY2026) | F5: Partner organization (if any) | G5: Funding source(s) | H5: Open to students from other districts? | I5: Annual cost ($), if known | J5: What makes it distinctive / why it matters to the community | K5: Contact | L5: Notes
A6: =IF(B6="","",'Read Me'!$C$5)
A7: =IF(B7="","",'Read Me'!$C$5)
A8: =IF(B8="","",'Read Me'!$C$5)
A9: =IF(B9="","",'Read Me'!$C$5)
A10: =IF(B10="","",'Read Me'!$C$5)
A11: =IF(B11="","",'Read Me'!$C$5)
A12: =IF(B12="","",'Read Me'!$C$5)
A13: =IF(B13="","",'Read Me'!$C$5)
A14: =IF(B14="","",'Read Me'!$C$5)
A15: =IF(B15="","",'Read Me'!$C$5)
A16: =IF(B16="","",'Read Me'!$C$5)
A17: =IF(B17="","",'Read Me'!$C$5)
... A45: =IF(B45="","",'Read Me'!$C$5)

Sheet 8 Contracts, Debt & Property
A1: Contracts, Debt and Property
A2: Needed for: Phase 4 (articles of agreement). One row per collective bargaining agreement, contract, bond/note, lease or property. District column fills in automatically.
A3: ="District: "&IF('Read Me'!$C$5="","(choose your district on the Read Me tab)",'Read Me'!$C$5)&" | Yellow cells = enter data. Grey cells = calculated, do not edit." -> District: (choose your district on the Read Me tab) | Yellow cells = enter data. Grey cells = calculated, do not edit.
A5: District | B5: Type | C5: Name / description | D5: Counterparty or bargaining unit | E5: Start date | F5: Expiration / maturity date | G5: Amount ($) / principal outstanding | H5: Annual payment ($) | I5: Key terms relevant to merger (e.g., successor clauses, seniority, call provisions) | J5: Owner of record | K5: Source document | L5: Notes
A6: =IF(B6="","",'Read Me'!$C$5)
A7: =IF(B7="","",'Read Me'!$C$5)
A8: =IF(B8="","",'Read Me'!$C$5)
A9: =IF(B9="","",'Read Me'!$C$5)
A10: =IF(B10="","",'Read Me'!$C$5)
A11: =IF(B11="","",'Read Me'!$C$5)
A12: =IF(B12="","",'Read Me'!$C$5)
A13: =IF(B13="","",'Read Me'!$C$5)
A14: =IF(B14="","",'Read Me'!$C$5)
A15: =IF(B15="","",'Read Me'!$C$5)
A16: =IF(B16="","",'Read Me'!$C$5)
A17: =IF(B17="","",'Read Me'!$C$5)
... A35: =IF(B35="","",'Read Me'!$C$5)

Sheet Lists
A1: Status | B1: ProgramCat | C1: District | D1: YesNo | E1: Condition | F1: CDPType
A2: Not started | B2: Academic | C2: Burlington | D2: Yes | E2: Good | F2: Collective bargaining agreement
A3: In progress | B3: Career & technical | C3: South Burlington | D3: No | E3: Fair | F3: Individual contract
A4: Submitted | B4: Arts | C4: Winooski | D4: Partly | E4: Poor | F4: Bond / note
A5: Not available | B5: Athletics & activities | E5: Critical | F5: Lease
B6: Special education | F6: Service contract
B7: Multilingual learners | F7: Real property
B8: Early childhood / PreK | F8: Other
B9: Before & after school
B10: Health & mental health
B11: Family & community partnership
B12: Other
